example_benchmarks/__init__.py
example_benchmarks/mock_test.py
semtest/__init__.py
semtest/__main__.py
semtest/config.py
semtest/py.typed
semtest/semtest.py
semtest/benchmarking/__init__.py
semtest/benchmarking/benchmark.py
semtest/benchmarking/metrics.py
semtest/comparator/__init__.py
semtest/comparator/core.py
semtest/comparator/semantic_comparator.py
semtest/embeddings/__init__.py
semtest/embeddings/core.py
semtest/embeddings/openai_embeddings.py
semtest/engine/__init__.py
semtest/engine/engine.py
semtest/loader/__init__.py
semtest/loader/loader.py
semtest/parser/__init__.py
semtest/parser/input_type.py
semtest/parser/paramspec.py
semtest/parser/parser.py
semtest/reporting/__init__.py
semtest/reporting/benchmark_report.py
semtest-0.0.1.dist-info/METADATA
semtest-0.0.1.dist-info/WHEEL
semtest-0.0.1.dist-info/entry_points.txt
semtest-0.0.1.dist-info/top_level.txt
semtest-0.0.1.dist-info/RECORD
