Metadata-Version: 2.4
Name: semtest
Version: 0.0.1
Summary: LLM semantic testing and benchmarking framework
Author: Cody Pedersen
Classifier: Programming Language :: Python :: 3.12
Classifier: Operating System :: OS Independent
Classifier: Intended Audience :: Developers
Classifier: Intended Audience :: Science/Research
Requires-Python: >=3.12
Requires-Dist: openai==1.44.0
Requires-Dist: scikit-learn==1.5.1
Requires-Dist: pydantic-settings==2.4.0
Requires-Dist: pydantic==2.9.0
Requires-Dist: tabulate==0.9.0
Requires-Dist: pandas==2.2.2
Requires-Dist: termcolor==2.4.0
Dynamic: author
Dynamic: classifier
Dynamic: description
Dynamic: description-content-type
Dynamic: requires-dist
Dynamic: requires-python
Dynamic: summary
